MANIFEST.in
README.md
setup.py
steam_comments/__init__.py
steam_comments/post.py
steam_comments.egg-info/PKG-INFO
steam_comments.egg-info/SOURCES.txt
steam_comments.egg-info/dependency_links.txt
steam_comments.egg-info/requires.txt
steam_comments.egg-info/top_level.txt