Metadata-Version: 1.1
Name: steam-comments
Version: 0.0.1
Summary: Steal commentaries from steam community
Home-page: https://github.com/xacce/steam_comments
Author: Xacce
Author-email: thiscie@gmail.com
License: MIT
Keywords: s,t,e,a,m, ,p,a,r,s,e,r, ,c,o,m,m,e,n,t,s
Platform: UNKNOWN
Classifier: Development Status :: 4 - Beta
Classifier: Intended Audience :: Developers
Classifier: License :: OSI Approved :: MIT License
Classifier: Programming Language :: Python :: 2.7
